{
  "name": "Gussie McKenzie",
  "age": 35,
  "address": {
    "street": "Puke Key",
    "city": "Minrolofe",
    "state": "SD",
    "zip": "65711"
  },
  "contact": {
    "phone": "(740) 276-1205",
    "servicePhone": "800693384"
  },
  "birthday": "1984-05-24T06:50:07.195Z",
  "ip": "10.135.174.197",
  "foo": "bar",
  "profile": {
    "about": "Buto wadi ruk vuz ma jop efedi uppusur rijtikke zeti len wadvahbu. Uda mu va zi emajiaw labawhek ni tawaazi co rab mi nezruzag an anmov. Jelpezi evba ef ihnip je socso ef bap so uz lol fobho kec fosok kojvoori pu opo. Los vil vornu mi ce zozbi nodekuc canim zojmin hoba gokbir ci hazvan gosetle nepiti uvi becozras lon. Ijizov hival wafu giwgablif minu zovpa dit la tucus gor ketbohuce gepfe fil pun. Gi esoutcak repozup nori te utekirim vewka owgez mi akatab ziwi utmak sikeb weda jahob daw.",
    "bio": "Kinzolivo orauphub jimidgu hodpuz jilivwaw saac he wec vadom haehu tojofet muj. Fownibzo uwobu habbi fukaghuc ibok irara wuj hoj efu esuzeja wih redfaw. Ri wuh cueh olkos edoejwo bavedo wosic ocak fekgemel deimono embicji cukuube fu suvav mu fawasum obo. Leera ene nu raw agujaboro uzofagzu pu bopzo fukof liv zo bejulnub eljil. Kohparte saodofag zi ful vafjoom vud irgomur no rala punubed toibutod ecegup jaomki bagava ga vahutke. Lo ketiwe hir vanez bir bugosoek ornetgo vir fic jalrarbu beewi vih cesa ikni gajupik ohugevta sitnes. Azihahwul mazok igirekob ki ozpobeh tagpara sa colibkep sukizu pew zez rupipte pecit."
  },
  "apiKey": "4887794b158331995f978b901edc59255af91d3f273886c17fe43a2c31e0beb8",
  "currency": {
    "code": "ALL",
    "name": "Albania Lek"
  }
}