{
  "name": "John Francis",
  "age": 37,
  "address": {
    "street": "Cafji Road",
    "city": "Erkazu",
    "state": "NM",
    "zip": "38974"
  },
  "contact": {
    "phone": "(344) 924-8537",
    "servicePhone": "800272296"
  },
  "birthday": "1977-06-01T04:25:21.474Z",
  "ip": "124.102.97.101",
  "foo": "bar",
  "profile": {
    "about": "Tobmum socage sodafu onoli cobcuure zipaba iggabuj vo zal uvobe bi dovnehug gebajruv vuno god ubi. Opiwok du pofta debberedi edovambul ewu dakefu moklogsih ed wunmelda lukko daz sugemod je rudvev pawvoop utuhejnu. Zucujuz jim loesas loor li im suj kojdelo forihos liguk in boufo nuhuv nanok. Ralok avalec zenowiw siunku tesnomte pal bifi sobnu iklu valni lacib ribhab refalfo haikon hiwiz tabjo lampa. Nohi bijijwib fiwcifaf waat rudobgul aploj jizjowo zeis epiwu gu hi wulgoz tafod inerma bi epa mufwelew fo. Fumvu zu ku sur gifohju ebufueru ni dacabbu da gizicuhes ko jide guje je fucsob doobebo. Zucnuhedi edumodte ciku ba fehne nizacu to bagec dargijer aciwed ralvodebu kisco vu biluzhug umu.",
    "bio": "Otfivip ciimo hiamebe gi bonfemiv ka na ju ba ala dal bakosis. No lolsijze li rorelak kovip wecnam deota fuit riezapo ribmic kildukhu tetibah. Kobzaid uznuzwuk penogbew liew banroho uru sonika zitzovpec wobockak piw usamithan pu fijehfe sah wurca dopi cap."
  },
  "apiKey": "5704d1ac9fb45dff1d438e47483ba45371dc3d5759681704efa0b0b75773b442",
  "currency": {
    "code": "MDL",
    "name": "Moldova Leu"
  }
}